dataclr/__init__.py
dataclr/_console_ui.py
dataclr/_evaluate.py
dataclr/_typing.py
dataclr/feature_selector/__init__.py
dataclr/feature_selector/_graph.py
dataclr/feature_selector/_graph_node.py
dataclr/feature_selector/_hash.py
dataclr/feature_selector/feature_selector.py
dataclr/methods/__init__.py
dataclr/methods/_method_list.py
dataclr/methods/anova_filter.py
dataclr/methods/boruta_wrapper.py
dataclr/methods/cdf_filter.py
dataclr/methods/chi2_filter.py
dataclr/methods/cohens_d_filter.py
dataclr/methods/cramers_v_filter.py
dataclr/methods/distance_correlation_filter.py
dataclr/methods/entropy_filter.py
dataclr/methods/filter_method.py
dataclr/methods/hyperopt_wrapper.py
dataclr/methods/kendall_correlation_filter.py
dataclr/methods/kurtosis_filter.py
dataclr/methods/linear_correlation_filter.py
dataclr/methods/mad_filter.py
dataclr/methods/method.py
dataclr/methods/mic_filter.py
dataclr/methods/mrmr_filter.py
dataclr/methods/mutual_information_filter.py
dataclr/methods/optuna_wrapper.py
dataclr/methods/rfa_wrapper.py
dataclr/methods/rfe_wrapper.py
dataclr/methods/shap_wrapper.py
dataclr/methods/skewness_filter.py
dataclr/methods/spearman_correlation_filter.py
dataclr/methods/variance_threshold_filter.py
dataclr/methods/vif_filter.py
dataclr/methods/wrapper_method.py
dataclr/methods/z_score_filter.py
dataclr/metrics/__init__.py
dataclr/metrics/metrics.py
dataclr/models/__init__.py
dataclr/models/model.py
dataclr/results/__init__.py
dataclr/results/performance.py
dataclr/results/result.py
dataclr-0.3.0.dist-info/LICENSE
dataclr-0.3.0.dist-info/LICENSE_THIRD_PARTY
dataclr-0.3.0.dist-info/METADATA
dataclr-0.3.0.dist-info/WHEEL
dataclr-0.3.0.dist-info/top_level.txt
dataclr-0.3.0.dist-info/RECORD
