Metadata-Version: 2.2
Name: dataclr
Version: 0.3.0
Summary: A Python library for feature selection in tabular datasets
Author-email: Lukasz Machutt <lukasz.machutt@gmail.com>, Jakub Nurkiewicz <jakub.nurkiewicz.2003@gmail.com>
Project-URL: Homepage, https://github.com/dataclr/dataclr
Project-URL: Documentation, https://www.dataclr.com
Keywords: feature selection,data science,machine learning,tabular data
Classifier: Development Status :: 4 - Beta
Classifier: Intended Audience :: Science/Research
Classifier: Intended Audience :: Developers
Classifier: Programming Language :: Python
Classifier: Programming Language :: Python :: 3.9
Classifier: Programming Language :: Python :: 3.10
Classifier: Programming Language :: Python :: 3.11
Classifier: Programming Language :: Python :: 3.12
Classifier: Programming Language :: Python :: 3.13
Classifier: Topic :: Scientific/Engineering :: Artificial Intelligence
Classifier: Topic :: Scientific/Engineering :: Information Analysis
Requires-Python: >=3.9
License-File: LICENSE
License-File: LICENSE_THIRD_PARTY
Requires-Dist: scikit-learn>=1.6.0
Requires-Dist: numpy>=2.0.2
Requires-Dist: pandas>=2.2.3
Requires-Dist: tqdm>=4.67.1
Requires-Dist: optuna>=4.1.0
Requires-Dist: dcor>=0.6
Requires-Dist: statsmodels>=0.14.4
Requires-Dist: setuptools>=62.0.0
Requires-Dist: numba<0.61.0,>=0.60.0; python_version < "3.13"
Requires-Dist: numba>=0.61.0rc2; python_version >= "3.13"
Requires-Dist: shap>=0.46.0
Requires-Dist: hyperopt>=0.2.7
Requires-Dist: Boruta>=0.4.3
Provides-Extra: dev
Requires-Dist: black==24.8.0; extra == "dev"
Requires-Dist: flake8==7.1.0; extra == "dev"
Requires-Dist: isort==5.13.2; extra == "dev"
Requires-Dist: pre-commit>=4.0.1; extra == "dev"
Provides-Extra: docs
Requires-Dist: sphinx>=5.0.0; extra == "docs"
Requires-Dist: sphinxawesome-theme>=2.0.0; extra == "docs"
Provides-Extra: test
Requires-Dist: pytest>=8.3.4; extra == "test"
